robin_local_logger/__init__.py
robin_local_logger/handler.py
robin_local_logger-0.1.1.dist-info/METADATA
robin_local_logger-0.1.1.dist-info/WHEEL
robin_local_logger-0.1.1.dist-info/top_level.txt
robin_local_logger-0.1.1.dist-info/RECORD
