Metadata-Version: 2.4
Name: robin-local-logger
Version: 0.1.1
Summary: A local file logger with automatic size trimming and standalone server support.
License: MIT
Keywords: fastapi,logging,json-logs,local-storage
Classifier: Programming Language :: Python :: 3
Classifier: Framework :: FastAPI
Classifier: License :: OSI Approved :: MIT License
Requires-Python: >=3.8
Requires-Dist: fastapi>=0.95.0
Requires-Dist: uvicorn>=0.18.0
Provides-Extra: dev
Requires-Dist: pytest; extra == "dev"
Requires-Dist: httpx; extra == "dev"
Requires-Dist: uvicorn; extra == "dev"
